README.md
setup.cfg
setup.py
elph/__init__.py
elph/__main__.py
elph/javerage.py
elph/main.py
elph/molecules.py
elph/phonons.py
elph/sigma.py
elph/visualization.py
elph.egg-info/PKG-INFO
elph.egg-info/SOURCES.txt
elph.egg-info/dependency_links.txt
elph.egg-info/entry_points.txt
elph.egg-info/requires.txt
elph.egg-info/top_level.txt