Metadata-Version: 2.1
Name: elph
Version: 1.0
Summary: Electron Phonon coupling within the Transient Localization Theory
Home-page: https://github.com/lucassamir/ElPh
Author: Lucas Cavalcante
Author-email: lsrcavalcante@ucdavis.edu
License: UNKNOWN
Platform: UNKNOWN
Classifier: Development Status :: 2 - Pre-Alpha
Classifier: Environment :: Console
Classifier: License :: OSI Approved :: GNU General Public License v3 or later (GPLv3+)
Classifier: Operating System :: Unix
Classifier: Programming Language :: Python :: 3 :: Only
Classifier: Programming Language :: Python :: 3.8
Classifier: Topic :: Scientific/Engineering :: Physics
Provides-Extra: docs
